[
{"city": "Aberdeen", "state": "Maryland"},
{"city": "Accokeek", "state": "Maryland"},
{"city": "Adelphi", "state": "Maryland"},
{"city": "Andrews AFB", "state": "Maryland"},
{"city": "Annapolis", "state": "Maryland"},
{"city": "Arbutus", "state": "Maryland"},
{"city": "Arnold", "state": "Maryland"},
{"city": "Aspen Hill", "state": "Maryland"},
{"city": "Ballenger Creek", "state": "Maryland"},
{"city": "Baltimore", "state": "Maryland"},
{"city": "Bel Air", "state": "Maryland"},
{"city": "Bel Air North", "state": "Maryland"},
{"city": "Bel Air South", "state": "Maryland"},
{"city": "Beltsville", "state": "Maryland"},
{"city": "Bennsville", "state": "Maryland"},
{"city": "Bethesda", "state": "Maryland"},
{"city": "Bladensburg", "state": "Maryland"},
{"city": "Bowie", "state": "Maryland"},
{"city": "Bowleys Quarters", "state": "Maryland"},
{"city": "Brooklyn Park", "state": "Maryland"},
{"city": "Burtonsville", "state": "Maryland"},
{"city": "California", "state": "Maryland"},
{"city": "Calverton", "state": "Maryland"},
{"city": "Cambridge", "state": "Maryland"},
{"city": "Camp Springs", "state": "Maryland"},
{"city": "Cape St. Claire", "state": "Maryland"},
{"city": "Carney", "state": "Maryland"},
{"city": "Catonsville", "state": "Maryland"},
{"city": "Chesapeake Ranch Estates-Drum Point", "state": "Maryland"},
{"city": "Cheverly", "state": "Maryland"},
{"city": "Chevy Chase", "state": "Maryland"},
{"city": "Chillum", "state": "Maryland"},
{"city": "Clinton", "state": "Maryland"},
{"city": "Cloverly", "state": "Maryland"},
{"city": "Cockeysville", "state": "Maryland"},
{"city": "Colesville", "state": "Maryland"},
{"city": "College Park", "state": "Maryland"},
{"city": "Columbia", "state": "Maryland"},
{"city": "Coral Hills", "state": "Maryland"},
{"city": "Crofton", "state": "Maryland"},
{"city": "Cumberland", "state": "Maryland"},
{"city": "Damascus", "state": "Maryland"},
{"city": "Darnestown", "state": "Maryland"},
{"city": "Dundalk", "state": "Maryland"},
{"city": "East Riverdale", "state": "Maryland"},
{"city": "Easton", "state": "Maryland"},
{"city": "Edgemere", "state": "Maryland"},
{"city": "Edgewood", "state": "Maryland"},
{"city": "Eldersburg", "state": "Maryland"},
{"city": "Elkridge", "state": "Maryland"},
{"city": "Elkton", "state": "Maryland"},
{"city": "Ellicott City", "state": "Maryland"},
{"city": "Essex", "state": "Maryland"},
{"city": "Fairland", "state": "Maryland"},
{"city": "Fallston", "state": "Maryland"},
{"city": "Ferndale", "state": "Maryland"},
{"city": "Forest Glen", "state": "Maryland"},
{"city": "Forestville", "state": "Maryland"},
{"city": "Fort Meade", "state": "Maryland"},
{"city": "Fort Washington", "state": "Maryland"},
{"city": "Frederick", "state": "Maryland"},
{"city": "Friendly", "state": "Maryland"},
{"city": "Frostburg", "state": "Maryland"},
{"city": "Gaithersburg", "state": "Maryland"},
{"city": "Garrison", "state": "Maryland"},
{"city": "Germantown", "state": "Maryland"},
{"city": "Glen Burnie", "state": "Maryland"},
{"city": "Glenarden", "state": "Maryland"},
{"city": "Glenn Dale", "state": "Maryland"},
{"city": "Greater Landover", "state": "Maryland"},
{"city": "Greater Upper Marlboro", "state": "Maryland"},
{"city": "Green Haven", "state": "Maryland"},
{"city": "Green Valley", "state": "Maryland"},
{"city": "Greenbelt", "state": "Maryland"},
{"city": "Hagerstown", "state": "Maryland"},
{"city": "Halfway", "state": "Maryland"},
{"city": "Havre de Grace", "state": "Maryland"},
{"city": "Hillcrest Heights", "state": "Maryland"},
{"city": "Hyattsville", "state": "Maryland"},
{"city": "Jessup", "state": "Maryland"},
{"city": "Joppatowne", "state": "Maryland"},
{"city": "Kemp Mill", "state": "Maryland"},
{"city": "Kettering", "state": "Maryland"},
{"city": "La Plata", "state": "Maryland"},
{"city": "Lake Arbor", "state": "Maryland"},
{"city": "Lake Shore", "state": "Maryland"},
{"city": "Langley Park", "state": "Maryland"},
{"city": "Lanham-Seabrook", "state": "Maryland"},
{"city": "Lansdowne-Baltimore Highlands", "state": "Maryland"},
{"city": "Largo", "state": "Maryland"},
{"city": "Laurel", "state": "Maryland"},
{"city": "Lexington Park", "state": "Maryland"},
{"city": "Linganore-Bartonsville", "state": "Maryland"},
{"city": "Linthicum", "state": "Maryland"},
{"city": "Lochearn", "state": "Maryland"},
{"city": "Londontowne", "state": "Maryland"},
{"city": "Lutherville-Timonium", "state": "Maryland"},
{"city": "Marlow Heights", "state": "Maryland"},
{"city": "Marlton", "state": "Maryland"},
{"city": "Maryland City", "state": "Maryland"},
{"city": "Maryland Heights", "state": "Missouri"},
{"city": "Mays Chapel", "state": "Maryland"},
{"city": "Middle River", "state": "Maryland"},
{"city": "Milford Mill", "state": "Maryland"},
{"city": "Mitchellville", "state": "Maryland"},
{"city": "Montgomery Village", "state": "Maryland"},
{"city": "Mount Airy", "state": "Maryland"},
{"city": "Mount Rainier", "state": "Maryland"},
{"city": "New Carrollton", "state": "Maryland"},
{"city": "North Bethesda", "state": "Maryland"},
{"city": "North Kensington", "state": "Maryland"},
{"city": "North Laurel", "state": "Maryland"},
{"city": "North Potomac", "state": "Maryland"},
{"city": "Ocean City", "state": "Maryland"},
{"city": "Ocean Pines", "state": "Maryland"},
{"city": "Odenton", "state": "Maryland"},
{"city": "Olney", "state": "Maryland"},
{"city": "Overlea", "state": "Maryland"},
{"city": "Owings Mills", "state": "Maryland"},
{"city": "Oxon Hill-Glassmanor", "state": "Maryland"},
{"city": "Parkville", "state": "Maryland"},
{"city": "Parole", "state": "Maryland"},
{"city": "Pasadena", "state": "Maryland"},
{"city": "Perry Hall", "state": "Maryland"},
{"city": "Pikesville", "state": "Maryland"},
{"city": "Potomac", "state": "Maryland"},
{"city": "Randallstown", "state": "Maryland"},
{"city": "Redland", "state": "Maryland"},
{"city": "Reisterstown", "state": "Maryland"},
{"city": "Riverdale Park", "state": "Maryland"},
{"city": "Riverside", "state": "Maryland"},
{"city": "Riviera Beach", "state": "Maryland"},
{"city": "Rockville", "state": "Maryland"},
{"city": "Rosaryville", "state": "Maryland"},
{"city": "Rosedale", "state": "Maryland"},
{"city": "Rossmoor", "state": "Maryland"},
{"city": "Rossville", "state": "Maryland"},
{"city": "Salisbury", "state": "Maryland"},
{"city": "Savage-Guilford", "state": "Maryland"},
{"city": "Severn", "state": "Maryland"},
{"city": "Severna Park", "state": "Maryland"},
{"city": "Silver Spring", "state": "Maryland"},
{"city": "South Gate", "state": "Maryland"},
{"city": "South Kensington", "state": "Maryland"},
{"city": "South Laurel", "state": "Maryland"},
{"city": "St. Charles", "state": "Maryland"},
{"city": "Suitland-Silver Hill", "state": "Maryland"},
{"city": "Takoma Park", "state": "Maryland"},
{"city": "Temple Hills", "state": "Maryland"},
{"city": "Towson", "state": "Maryland"},
{"city": "Travilah", "state": "Maryland"},
{"city": "Waldorf", "state": "Maryland"},
{"city": "Walker Mill", "state": "Maryland"},
{"city": "Westminster", "state": "Maryland"},
{"city": "Wheaton-Glenmont", "state": "Maryland"},
{"city": "White Marsh", "state": "Maryland"},
{"city": "White Oak", "state": "Maryland"},
{"city": "Woodlawn", "state": "Maryland"},
{"city": "Woodlawn", "state": "Maryland"},
{"city": "Woodmore", "state": "Maryland"}
]
